py_react_django/__init__.py
py_react_django/apps.py
py_react_django/components/app.jsx
py_react_django/generic.py
py_react_django/mixins.py
py_react_django/templates/py_react_django/react.html
py_react_django/templates/py_react_django/react_props.html
py_react_django/templatetags/react_tags.py
py_react_django-0.2.0.dist-info/METADATA
py_react_django-0.2.0.dist-info/WHEEL
py_react_django-0.2.0.dist-info/RECORD
